lynxinven/__init__.py
lynxinven/api.py
lynxinven/base.py
lynxinven/build.py
lynxinven/company.py
lynxinven/order.py
lynxinven/part.py
lynxinven/stock.py
scripts/__init__.py
scripts/test_server_connection.py
test/__init__.py
test/test_api.py
test/test_company.py
test/test_order.py
test/test_part.py
test/test_stock.py
lynxinven-0.4.4.dist-info/METADATA
lynxinven-0.4.4.dist-info/WHEEL
lynxinven-0.4.4.dist-info/top_level.txt
lynxinven-0.4.4.dist-info/RECORD
