Metadata-Version: 2.1
Name: lynxinven
Version: 0.4.4
Summary: Python interface for LynxInven inventory management system
Home-page: https://github.com/Lynx-Solve/lynxinven-python/
Author: Jason Menzies
Author-email: info@lynxsolve.com
License: MIT
Keywords: bom,bill of materials,stock,inventory,management,barcode
Platform: UNKNOWN
Requires-Python: >=3.6
Requires-Dist: requests
